setup.py
mnl_probability/Binomialdistribution.py
mnl_probability/Gaussiandistribution.py
mnl_probability/Generaldistribution.py
mnl_probability/__init__.py
mnl_probability.egg-info/PKG-INFO
mnl_probability.egg-info/SOURCES.txt
mnl_probability.egg-info/dependency_links.txt
mnl_probability.egg-info/not-zip-safe
mnl_probability.egg-info/top_level.txt