Metadata-Version: 1.0
Name: mnl-probability
Version: 0.1
Summary: Gaussian and Binomial distributions
Home-page: UNKNOWN
Author: Marcel Lucero
Author-email: mluceron@gmail.com
License: UNKNOWN
Platform: UNKNOWN
